scottzach1/semantic_release/__init__.py
gh_semantic_release-0.0.1.dist-info/LICENSE
gh_semantic_release-0.0.1.dist-info/METADATA
gh_semantic_release-0.0.1.dist-info/WHEEL
gh_semantic_release-0.0.1.dist-info/top_level.txt
gh_semantic_release-0.0.1.dist-info/RECORD
