Metadata-Version: 2.2
Name: gh-semantic-release
Version: 0.0.1
Summary: Trigger a semantic release with the click of a button
Author-email: Zac Scott <zac.scott11@gmail.com>
License: BSD-3
Requires-Python: >=3.11
License-File: LICENSE
